supress/__init__.py
supress-1.3.1.dist-info/LICENSE
supress-1.3.1.dist-info/METADATA
supress-1.3.1.dist-info/WHEEL
supress-1.3.1.dist-info/top_level.txt
supress-1.3.1.dist-info/RECORD
