Metadata-Version: 2.1
Name: supress
Version: 1.3.1
Summary: A simple utility to supress output
Home-page: https://github.com/vcokltfre/Supress
Author: vcokltfre
License: MIT
Platform: UNKNOWN
Requires-Python: >=3.4
